{
  "Tool Name": "OWASP ZAP",
  "Speakers": [
    "Simon Bennetts"
  ],
  "Tracks": [
    "Track: Web AppSec"
  ],
  "Event": "BH-EU-17",
  "Github URL": "https://github.com/psiinon",
  "Description": "The Zed Attack Proxy (ZAP) is currently the most active open source web application security tool and was voted the top security tool in the last Toolswatch annual survey. While it is an ideal tool for people new to appsec it also has many features specifically intended for advanced penetration testing. Simon will give a quick introduction to ZAP and then dive into the more advanced features as well as giving an overview of where its heading.",
  "Year": "2017",
  "Location": "Europe"
}